liquidData/__init__.py
liquidData/dataFrames.py
liquidData/liquidData.py
liquidData-0.1.0.dist-info/LICENSE
liquidData-0.1.0.dist-info/METADATA
liquidData-0.1.0.dist-info/WHEEL
liquidData-0.1.0.dist-info/top_level.txt
liquidData-0.1.0.dist-info/RECORD
