Metadata-Version: 2.1
Name: liquidData
Version: 0.1.0
Summary: a bunch of code for data analysis
Home-page: https://github.com/Limthu/liquidData
Author: Alexander Kast
Author-email: alexander.kast@mailbox.org
License: MIT license
Keywords: liquidData
Classifier: Development Status :: 2 - Pre-Alpha
Classifier: Intended Audience :: Developers
Classifier: License :: OSI Approved :: MIT License
Classifier: Natural Language :: English
Classifier: Programming Language :: Python :: 3
Classifier: Programming Language :: Python :: 3.6
Classifier: Programming Language :: Python :: 3.7
Classifier: Programming Language :: Python :: 3.8
Requires-Python: >=3.6
License-File: LICENSE
